odoo8_addon_web_favicon-8.0.1.0.0.99.dev17-py2.7-nspkg.pth
odoo8_addon_web_favicon-8.0.1.0.0.99.dev17.dist-info/DESCRIPTION.rst
odoo8_addon_web_favicon-8.0.1.0.0.99.dev17.dist-info/METADATA
odoo8_addon_web_favicon-8.0.1.0.0.99.dev17.dist-info/RECORD
odoo8_addon_web_favicon-8.0.1.0.0.99.dev17.dist-info/WHEEL
odoo8_addon_web_favicon-8.0.1.0.0.99.dev17.dist-info/metadata.json
odoo8_addon_web_favicon-8.0.1.0.0.99.dev17.dist-info/namespace_packages.txt
odoo8_addon_web_favicon-8.0.1.0.0.99.dev17.dist-info/top_level.txt
odoo_addons/web_favicon/README.rst
odoo_addons/web_favicon/__init__.py
odoo_addons/web_favicon/__openerp__.py
odoo_addons/web_favicon/controllers/__init__.py
odoo_addons/web_favicon/controllers/web_favicon.py
odoo_addons/web_favicon/i18n/am.po
odoo_addons/web_favicon/i18n/ar.po
odoo_addons/web_favicon/i18n/ca.po
odoo_addons/web_favicon/i18n/de.po
odoo_addons/web_favicon/i18n/el_GR.po
odoo_addons/web_favicon/i18n/es.po
odoo_addons/web_favicon/i18n/es_ES.po
odoo_addons/web_favicon/i18n/es_MX.po
odoo_addons/web_favicon/i18n/eu.po
odoo_addons/web_favicon/i18n/fi.po
odoo_addons/web_favicon/i18n/fr.po
odoo_addons/web_favicon/i18n/fr_FR.po
odoo_addons/web_favicon/i18n/hr.po
odoo_addons/web_favicon/i18n/hr_HR.po
odoo_addons/web_favicon/i18n/id.po
odoo_addons/web_favicon/i18n/it.po
odoo_addons/web_favicon/i18n/nb.po
odoo_addons/web_favicon/i18n/nb_NO.po
odoo_addons/web_favicon/i18n/nl.po
odoo_addons/web_favicon/i18n/nl_BE.po
odoo_addons/web_favicon/i18n/nl_NL.po
odoo_addons/web_favicon/i18n/pt_BR.po
odoo_addons/web_favicon/i18n/ro.po
odoo_addons/web_favicon/i18n/sk.po
odoo_addons/web_favicon/i18n/sl.po
odoo_addons/web_favicon/i18n/tr.po
odoo_addons/web_favicon/i18n/web_favicon.pot
odoo_addons/web_favicon/i18n/zh_CN.po
odoo_addons/web_favicon/models/__init__.py
odoo_addons/web_favicon/models/res_company.py
odoo_addons/web_favicon/static/description/icon.png
odoo_addons/web_favicon/static/src/img/android-chrome-144x144.png
odoo_addons/web_favicon/static/src/img/android-chrome-192x192.png
odoo_addons/web_favicon/static/src/img/android-chrome-36x36.png
odoo_addons/web_favicon/static/src/img/android-chrome-48x48.png
odoo_addons/web_favicon/static/src/img/android-chrome-72x72.png
odoo_addons/web_favicon/static/src/img/android-chrome-96x96.png
odoo_addons/web_favicon/static/src/img/apple-touch-icon-114x114.png
odoo_addons/web_favicon/static/src/img/apple-touch-icon-120x120.png
